./.gitignore
./.markdownlint.json
./Dockerfile
./LICENSE
./README.md
./pyproject.toml
./run.py
./.github/workflows/lint.yaml
./.github/workflows/publish_docker.yaml
./apricot/__about__.py
./apricot/__init__.py
./apricot/apricot_server.py
./apricot/typedefs.py
./apricot/cache/__init__.py
./apricot/cache/local_cache.py
./apricot/cache/redis_cache.py
./apricot/cache/uid_cache.py
./apricot/ldap/__init__.py
./apricot/ldap/oauth_ldap_entry.py
./apricot/ldap/oauth_ldap_server_factory.py
./apricot/ldap/oauth_ldap_tree.py
./apricot/ldap/read_only_ldap_server.py
./apricot/models/__init__.py
./apricot/models/ldap_attribute_adaptor.py
./apricot/models/ldap_group_of_names.py
./apricot/models/ldap_inetorgperson.py
./apricot/models/ldap_object_class.py
./apricot/models/ldap_organizational_person.py
./apricot/models/ldap_person.py
./apricot/models/ldap_posix_account.py
./apricot/models/ldap_posix_group.py
./apricot/models/overlay_memberof.py
./apricot/models/overlay_oauthentry.py
./apricot/oauth/__init__.py
./apricot/oauth/enums.py
./apricot/oauth/keycloak_client.py
./apricot/oauth/microsoft_entra_client.py
./apricot/oauth/oauth_client.py
./apricot/oauth/oauth_data_adaptor.py
./apricot/patches/__init__.py
./apricot/patches/ldap_string.py
./docker/docker-compose.yaml
./docker/entrypoint.sh
apricot_server-0.1.1.dist-info/METADATA
apricot_server-0.1.1.dist-info/WHEEL
apricot_server-0.1.1.dist-info/licenses/LICENSE
apricot_server-0.1.1.dist-info/RECORD
