Metadata-Version: 2.4
Name: apricot-server
Version: 0.1.1
Summary: A proxy for delegating LDAP requests to an OpenID Connect backend.
Project-URL: Documentation, https://github.com/alan-turing-institute/apricot#readme
Project-URL: Issues, https://github.com/alan-turing-institute/apricot/issues
Project-URL: Source, https://github.com/alan-turing-institute/apricot
Author-email: James Robinson <james.em.robinson@gmail.com>
License-Expression: BSD-3-Clause
License-File: LICENSE
Classifier: Development Status :: 4 - Beta
Classifier: Programming Language :: Python
Classifier: Programming Language :: Python :: 3.7
Classifier: Programming Language :: Python :: 3.8
Classifier: Programming Language :: Python :: 3.9
Classifier: Programming Language :: Python :: 3.10
Classifier: Programming Language :: Python :: 3.11
Classifier: Programming Language :: Python :: 3.12
Classifier: Programming Language :: Python :: Implementation :: CPython
Classifier: Programming Language :: Python :: Implementation :: PyPy
Requires-Python: >=3.7
Requires-Dist: ldaptor~=21.2
Requires-Dist: oauthlib~=3.2
Requires-Dist: pydantic~=2.4
Requires-Dist: redis~=5.0
Requires-Dist: requests-oauthlib~=1.3
Requires-Dist: twisted~=23.10
Requires-Dist: zope-interface~=6.2
